lazyconf
