Metadata-Version: 1.0
Name: lazyconf
Version: 0.5.5
Summary: Insultingly simple configuration for Python 2.7 applications.
Home-page: https://www.github.com/fmd/lazyconf
Author: Fareed Dudhia
Author-email: fareeddudhia@gmail.com
License: LICENSE.rst
Platform: UNKNOWN
